{"chunk_definitions":[{"row":18,"row_count":1,"visible":true,"expansion_state":0,"options":{"engine":"r","label":"unnamed-chunk-36","dev":"png"},"document_id":"0705B1E1","chunk_id":"c8tma3g80h86e","chunk_label":"unnamed-chunk-1"},{"row":26,"row_count":1,"visible":true,"expansion_state":0,"options":{"engine":"r","label":"unnamed-chunk-37","dev":"png"},"document_id":"0705B1E1","chunk_id":"c0f1w5vggecpn","chunk_label":"unnamed-chunk-2"},{"row":45,"row_count":1,"visible":true,"expansion_state":0,"options":{"engine":"r","label":"unnamed-chunk-38","dev":"png"},"document_id":"0705B1E1","chunk_id":"cj9mz3smsff4b","chunk_label":"unnamed-chunk-3"},{"row":63,"row_count":1,"visible":true,"expansion_state":0,"options":{"engine":"r","label":"unnamed-chunk-39","dev":"png"},"document_id":"0705B1E1","chunk_id":"ccmcniex330jt","chunk_label":"unnamed-chunk-4"},{"row":81,"row_count":1,"visible":true,"expansion_state":0,"options":{"engine":"r","label":"unnamed-chunk-40","dev":"png"},"document_id":"0705B1E1","chunk_id":"c57psw2uexp1v","chunk_label":"unnamed-chunk-5"},{"row":99,"row_count":1,"visible":true,"expansion_state":0,"options":{"engine":"r","label":"unnamed-chunk-41","dev":"png"},"document_id":"0705B1E1","chunk_id":"ck1elvaq86xcn","chunk_label":"unnamed-chunk-6"},{"row":182,"row_count":1,"visible":true,"expansion_state":0,"options":{"engine":"r","label":"unnamed-chunk-44","dev":"png"},"document_id":"0705B1E1","chunk_id":"cdxu48ev721u1","chunk_label":"unnamed-chunk-15"}],"doc_write_time":1725481866}